{
  "fulfils_needs" : {
    "label" : { 
      "en" : "Needs fulfilled by a community",
      "de" : "Erfüllte Bedürfnisse"
    },
    "description" : {
      "en" : "We all have needs. We need food and shelter, we need mobility and we need to communicate with others. Here is a list of various needs. You will find both: things that directly satisfy your needs as well as people who care for providing these things and for running needs-oriented projects",
      "de" : "Wir alle haben Bedürfnisse. Wir müssen essen und trinken, wir suchen Schutz, brauchen Wissen und Mobilität. Hier findet sich eine Liste dieser Bedürfnisse."
    },
    "items" : [ 
      {
        "transformap:key" : "food+drink",
        "osm:key" : "fulfils_needs:food+drink",
        "osm:values" : [ "yes" ],
        "label" : {
          "en" : "provides: food & drink",
          "de" : "Bietet: Essen & Getränke"
        },
        "description" : {
          "en" : "",
          "de" : ""
        },
        "osm:objects" : [ 
          { "amenity" : "pub" , "food" : "yes" } ,
          { "amenity" : "restaurant" } ,
          { "shop" : "butcher" },
          { "leisure" : "garden", "description" : "Gemeinschaftsgarten" }
        ]
      },
      {
        "transformap:key" : "water", 
        "osm:key" : "fulfils_needs:water",
        "osm:values" : [ "yes" ],
        "label" : {
          "en" : "provides: water",
          "de" : "Bietet: Wasser"
        },
        "description" : {
          "en" : "",
          "de" : ""
        },
        "osm:objects" : [ 
          { "amenity" : "drinking_water" } ,
          { "shop" : "butcher" },
          { "leisure" : "garden", "description" : "Gemeinschaftsgarten" }
        ]
      }

    ]
  }
}
